{
  "data_path": "/Users/ganeshtilekar/BTC_DATA/BTCUSDT_15m_All.csv",
  "bars": 310462,
  "start": "2017-08-17 04:00:00+00:00",
  "end": "2026-06-30 23:45:00+00:00",
  "n_features": 116,
  "model": "LightGBM",
  "folds": [
    {
      "year": 2019,
      "auc": 0.549845656377646,
      "acc": 0.6391362868352473,
      "n_test": 34919,
      "long_prec": 0.3651349380014588,
      "feature_top": [
        "d1_ret",
        "h4_rsi",
        "h4_ret",
        "d1_rsi",
        "hv_50",
        "adx_14",
        "hour",
        "dist_hh_96",
        "d1_ema200",
        "hv_20",
        "ret_89",
        "h4_ema200",
        "atr_ratio",
        "ret_55",
        "dist_ll_96"
      ]
    },
    {
      "year": 2020,
      "auc": 0.5334849365244712,
      "acc": 0.673019314712847,
      "n_test": 35051,
      "long_prec": 0.37920937042459735,
      "feature_top": [
        "d1_ret",
        "h4_rsi",
        "h4_ret",
        "d1_rsi",
        "hv_50",
        "d1_ema200",
        "adx_14",
        "hour",
        "dist_hh_96",
        "atr_ratio",
        "hv_20",
        "ret_89",
        "h4_ema200",
        "d1_ema50",
        "dist_hh_48"
      ]
    },
    {
      "year": 2021,
      "auc": 0.5354861084561944,
      "acc": 0.6263082642264799,
      "n_test": 34970,
      "long_prec": 0.35295670538542767,
      "feature_top": [
        "d1_ret",
        "h4_rsi",
        "h4_ret",
        "d1_rsi",
        "hv_50",
        "d1_ema200",
        "adx_14",
        "hour",
        "dist_hh_96",
        "atr_ratio",
        "ret_89",
        "h4_ema200",
        "hv_20",
        "d1_ema50",
        "dist_hh_48"
      ]
    },
    {
      "year": 2022,
      "auc": 0.5404404888318396,
      "acc": 0.6740296803652968,
      "n_test": 35040,
      "long_prec": 0.3838892385147892,
      "feature_top": [
        "d1_ret",
        "h4_rsi",
        "h4_ret",
        "d1_rsi",
        "hv_50",
        "d1_ema200",
        "adx_14",
        "hour",
        "dist_hh_96",
        "ret_89",
        "atr_ratio",
        "h4_ema200",
        "hv_20",
        "d1_ema50",
        "dow"
      ]
    },
    {
      "year": 2023,
      "auc": 0.5447006339473309,
      "acc": 0.6737082500713674,
      "n_test": 35030,
      "long_prec": 0.36797752808988765,
      "feature_top": [
        "d1_ret",
        "h4_rsi",
        "h4_ret",
        "d1_rsi",
        "hv_50",
        "d1_ema200",
        "adx_14",
        "hour",
        "dist_hh_96",
        "ret_89",
        "h4_ema200",
        "atr_ratio",
        "dow",
        "d1_ema50",
        "hv_20"
      ]
    },
    {
      "year": 2024,
      "auc": 0.5361677640501027,
      "acc": 0.6732411202185792,
      "n_test": 35136,
      "long_prec": 0.5117647058823529,
      "feature_top": [
        "d1_ret",
        "h4_rsi",
        "d1_rsi",
        "h4_ret",
        "hv_50",
        "d1_ema200",
        "adx_14",
        "hour",
        "dist_hh_96",
        "dow",
        "atr_ratio",
        "ret_89",
        "h4_ema200",
        "hv_20",
        "d1_ema50"
      ]
    },
    {
      "year": 2025,
      "auc": 0.5145644462713287,
      "acc": 0.6737157534246575,
      "n_test": 35040,
      "long_prec": 0.3284313725490196,
      "feature_top": [
        "d1_ret",
        "h4_rsi",
        "d1_rsi",
        "h4_ret",
        "hv_50",
        "d1_ema200",
        "adx_14",
        "hour",
        "dist_hh_96",
        "dow",
        "atr_ratio",
        "ret_89",
        "h4_ema200",
        "hv_20",
        "atr_28"
      ]
    },
    {
      "year": 2026,
      "auc": 0.5109187839524918,
      "acc": 0.690595629360549,
      "n_test": 17343,
      "long_prec": 0.24324324324324326,
      "feature_top": [
        "d1_ret",
        "h4_rsi",
        "d1_rsi",
        "h4_ret",
        "hv_50",
        "d1_ema200",
        "adx_14",
        "hour",
        "dist_hh_96",
        "dow",
        "atr_ratio",
        "ret_89",
        "atr_28",
        "h4_ema200",
        "hv_20"
      ]
    }
  ],
  "last_year_backtest": {
    "end_equity": 106740.9845645796,
    "return_pct": 6.740984564579611,
    "trades": 2716,
    "win_rate": 35.34609720176731,
    "max_dd_pct": -5.352048958821132
  },
  "year_stats": [
    {
      "end_equity": 115624.26407505525,
      "return_pct": 15.624264075055262,
      "trades": 4594,
      "win_rate": 35.30692207226818,
      "max_dd_pct": -7.521319545016247,
      "year": 2019
    },
    {
      "end_equity": 96044.13038410438,
      "return_pct": -3.955869615895613,
      "trades": 5009,
      "win_rate": 33.53962866839689,
      "max_dd_pct": -13.639286460566847,
      "year": 2020
    },
    {
      "end_equity": 166323.5056918349,
      "return_pct": 66.3235056918349,
      "trades": 4659,
      "win_rate": 35.6084996780425,
      "max_dd_pct": -6.11665965104441,
      "year": 2021
    },
    {
      "end_equity": 126278.46668158263,
      "return_pct": 26.278466681582625,
      "trades": 4439,
      "win_rate": 35.57107456634377,
      "max_dd_pct": -6.756131273198851,
      "year": 2022
    },
    {
      "end_equity": 101731.03366987374,
      "return_pct": 1.7310336698737272,
      "trades": 5200,
      "win_rate": 34.86538461538461,
      "max_dd_pct": -6.141698745673285,
      "year": 2023
    },
    {
      "end_equity": 103380.17093657448,
      "return_pct": 3.380170936574478,
      "trades": 5777,
      "win_rate": 34.221914488488835,
      "max_dd_pct": -7.332308133613963,
      "year": 2024
    },
    {
      "end_equity": 103633.28839104681,
      "return_pct": 3.6332883910468183,
      "trades": 5602,
      "win_rate": 34.416279900035704,
      "max_dd_pct": -8.354972508570368,
      "year": 2025
    },
    {
      "end_equity": 106658.71365319379,
      "return_pct": 6.658713653193793,
      "trades": 2699,
      "win_rate": 35.42052612078548,
      "max_dd_pct": -5.443839933203575,
      "year": 2026
    }
  ],
  "top_features": [
    "d1_ret",
    "h4_rsi",
    "d1_rsi",
    "h4_ret",
    "hv_50",
    "d1_ema200",
    "adx_14",
    "hour",
    "dist_hh_96",
    "dow",
    "atr_ratio",
    "ret_89",
    "atr_28",
    "h4_ema200",
    "hv_20",
    "d1_ema50",
    "dist_ll_96",
    "dist_hh_48",
    "h1_rsi",
    "ret_55",
    "dist_ll_48",
    "bb_width",
    "dist_ema_200",
    "h1_ema200",
    "dist_ll_24",
    "bb_std",
    "atr_pct",
    "month",
    "dist_hh_24",
    "macd_signal"
  ]
}